LICENSE
MANIFEST.in
README.md
package.json
setup.py
ordep/Ordep.py
ordep/__init__.py
ordep/_imports_.py
ordep/metadata.json
ordep/ordep.min.js
ordep/ordep.min.js.map
ordep/package-info.json
ordep.egg-info/PKG-INFO
ordep.egg-info/SOURCES.txt
ordep.egg-info/dependency_links.txt
ordep.egg-info/top_level.txt
tests/test_usage.py