Metadata-Version: 2.1
Name: ordep
Version: 0.0.1
Summary: React to Dash Components
Author: Pedro Lima <pmlima99@gmail.com>
License: MIT
Classifier: Framework :: Dash
License-File: LICENSE
